setup.py
EasyStats/Binomialdistribution.py
EasyStats/Gaussiandistribution.py
EasyStats/Generaldistribution.py
EasyStats/__init__.py
EasyStats.egg-info/PKG-INFO
EasyStats.egg-info/SOURCES.txt
EasyStats.egg-info/dependency_links.txt
EasyStats.egg-info/not-zip-safe
EasyStats.egg-info/top_level.txt