Metadata-Version: 1.0
Name: EasyStats
Version: 0.1
Summary: Gaussian and Binomial distributions
Home-page: UNKNOWN
Author: Rucha Yagnik
Author-email: UNKNOWN
License: UNKNOWN
Platform: UNKNOWN
